{
  "1476735211894210751": {
    "enabled": true,
    "channel_id": 1476851387819364372,
    "admin_role_ids": [
      1476765248856920125,
      1476738036694913106
    ],
    "timezone": "Europe/London",
    "server_streak": {
      "current": 2,
      "best": 31,
      "last_score_date": "2026-05-27"
    },
    "alerts": {
      "daily_post_enabled": true,
      "daily_scoreboard_enabled": true,
      "weekly_roundup_enabled": true,
      "rivalry_enabled": true,
      "monthly_leaderboard_enabled": true,
      "zero_score_roasts_enabled": true,
      "pb_messages_enabled": true,
      "perfect_score_enabled": true
    },
    "emojis": {
      "recorded": "<:maptapp:1476982463430660136>",
      "too_high": "\u274c",
      "rescan_ingested": "\ud83d\udd01",
      "config_issue": "\u26a0\ufe0f"
    },
    "times": {
      "daily_post": "00:01",
      "daily_scoreboard": "23:58",
      "weekly_roundup": "23:45",
      "rivalry": "14:00",
      "monthly_leaderboard": "00:05"
    },
    "minimum_days": {
      "this_week": 3,
      "this_month": 7,
      "all_time": 0,
      "date_range": 0
    },
    "last_run": {
      "daily_post": "2026-06-16",
      "daily_scoreboard": "2026-06-15",
      "weekly_roundup": "2026-05-31",
      "rivalry": "2026-06-20",
      "monthly_leaderboard": "2026-06-01"
    },
    "schedule": {
      "daily_post": "00:00",
      "daily_scoreboard": "23:30",
      "weekly_day": 6,
      "weekly_time": "23:45",
      "rivalry_day": 4,
      "rivalry_time": "19:30",
      "rivalry_gap": 25
    }
  },
  "1489660601545261148": {
    "enabled": false,
    "channel_id": 1489660602438914171,
    "admin_role_ids": [],
    "timezone": "Europe/London",
    "server_streak": {
      "current": 0,
      "best": 1,
      "last_score_date": "2026-04-05"
    },
    "alerts": {
      "daily_post_enabled": true,
      "daily_scoreboard_enabled": true,
      "weekly_roundup_enabled": true,
      "rivalry_enabled": true,
      "monthly_leaderboard_enabled": true,
      "zero_score_roasts_enabled": true,
      "pb_messages_enabled": true,
      "perfect_score_enabled": true
    },
    "emojis": {
      "recorded": "<:maptapp:1476982463430660136>",
      "too_high": "\u274c",
      "rescan_ingested": "\ud83d\udd01",
      "config_issue": "\u26a0\ufe0f"
    },
    "times": {
      "daily_post": "00:00",
      "daily_scoreboard": "23:30",
      "weekly_roundup": "23:45",
      "rivalry": "14:00",
      "monthly_leaderboard": "00:10"
    },
    "minimum_days": {
      "this_week": 3,
      "this_month": 7,
      "all_time": 0,
      "date_range": 0
    },
    "last_run": {
      "daily_post": "2026-04-07",
      "daily_scoreboard": "2026-04-17",
      "weekly_roundup": "2026-04-05",
      "rivalry": "2026-04-17",
      "monthly_leaderboard": null
    }
  },
  "1480706642310856798": {
    "enabled": true,
    "channel_id": 1489950479713697934,
    "admin_role_ids": [
      1489952993355890743
    ],
    "timezone": "Europe/London",
    "server_streak": {
      "current": 0,
      "best": 6,
      "last_score_date": "2026-04-09"
    },
    "alerts": {
      "daily_post_enabled": true,
      "daily_scoreboard_enabled": true,
      "weekly_roundup_enabled": true,
      "rivalry_enabled": true,
      "monthly_leaderboard_enabled": true,
      "zero_score_roasts_enabled": true,
      "pb_messages_enabled": true,
      "perfect_score_enabled": true
    },
    "emojis": {
      "recorded": "<:maptapp:1476982463430660136>",
      "too_high": "\u274c",
      "rescan_ingested": "\ud83d\udd01",
      "config_issue": "\u26a0\ufe0f"
    },
    "times": {
      "daily_post": "00:00",
      "daily_scoreboard": "23:30",
      "weekly_roundup": "23:45",
      "rivalry": "14:00",
      "monthly_leaderboard": "00:10"
    },
    "minimum_days": {
      "this_week": 3,
      "this_month": 7,
      "all_time": 0,
      "date_range": 0
    },
    "last_run": {
      "daily_post": "2026-06-16",
      "daily_scoreboard": "2026-06-15",
      "weekly_roundup": "2026-05-31",
      "rivalry": "2026-06-20",
      "monthly_leaderboard": "2026-06-01"
    }
  },
  "1472971490134720552": {
    "enabled": true,
    "channel_id": 1478696435204755608,
    "admin_role_ids": [
      1491520915484311726
    ],
    "timezone": "Europe/London",
    "server_streak": {
      "current": 1,
      "best": 26,
      "last_score_date": "2026-06-14"
    },
    "alerts": {
      "daily_post_enabled": true,
      "daily_scoreboard_enabled": true,
      "weekly_roundup_enabled": true,
      "rivalry_enabled": true,
      "monthly_leaderboard_enabled": true,
      "zero_score_roasts_enabled": true,
      "pb_messages_enabled": true,
      "perfect_score_enabled": true
    },
    "emojis": {
      "recorded": "<:maptapp:1476982463430660136>",
      "too_high": "\u274c",
      "rescan_ingested": "\ud83d\udd01",
      "config_issue": "\u26a0\ufe0f"
    },
    "times": {
      "daily_post": "00:00",
      "daily_scoreboard": "23:30",
      "weekly_roundup": "23:45",
      "rivalry": "14:00",
      "monthly_leaderboard": "00:10"
    },
    "minimum_days": {
      "this_week": 3,
      "this_month": 7,
      "all_time": 0,
      "date_range": 0
    },
    "last_run": {
      "daily_post": "2026-06-16",
      "daily_scoreboard": "2026-06-15",
      "weekly_roundup": "2026-05-31",
      "rivalry": "2026-06-20",
      "monthly_leaderboard": "2026-06-01"
    }
  },
  "230560367976251392": {
    "enabled": true,
    "channel_id": 1278574955671326730,
    "admin_role_ids": [
      758395459483467838
    ],
    "timezone": "PST8PDT",
    "server_streak": {
      "current": 3,
      "best": 3,
      "last_score_date": "2026-04-15"
    },
    "alerts": {
      "daily_post_enabled": true,
      "daily_scoreboard_enabled": true,
      "weekly_roundup_enabled": true,
      "rivalry_enabled": true,
      "monthly_leaderboard_enabled": true,
      "zero_score_roasts_enabled": true,
      "pb_messages_enabled": false,
      "perfect_score_enabled": true
    },
    "emojis": {
      "recorded": "<:maptapp:1476982463430660136>",
      "too_high": "\u274c",
      "rescan_ingested": "\ud83d\udd01",
      "config_issue": "\u26a0\ufe0f"
    },
    "times": {
      "daily_post": "00:00",
      "daily_scoreboard": "23:30",
      "weekly_roundup": "23:45",
      "rivalry": "14:00",
      "monthly_leaderboard": "00:10"
    },
    "minimum_days": {
      "this_week": 3,
      "this_month": 7,
      "all_time": 0,
      "date_range": 0
    },
    "last_run": {
      "daily_post": "2026-06-16",
      "daily_scoreboard": "2026-06-15",
      "weekly_roundup": "2026-06-14",
      "rivalry": "2026-06-03",
      "monthly_leaderboard": "2026-06-01"
    }
  },
  "1429129667280896062": {
    "enabled": true,
    "channel_id": 1429130661427679315,
    "admin_role_ids": [
      1445091811256303769,
      1430212727153885308
    ],
    "timezone": "Europe/Berlin",
    "server_streak": {
      "current": 1,
      "best": 1,
      "last_score_date": "2026-04-14"
    },
    "alerts": {
      "daily_post_enabled": false,
      "daily_scoreboard_enabled": true,
      "weekly_roundup_enabled": true,
      "rivalry_enabled": true,
      "monthly_leaderboard_enabled": true,
      "zero_score_roasts_enabled": true,
      "pb_messages_enabled": true,
      "perfect_score_enabled": true
    },
    "emojis": {
      "recorded": "<:maptapp:1476982463430660136>",
      "too_high": "\u274c",
      "rescan_ingested": "\ud83d\udd01",
      "config_issue": "\u26a0\ufe0f"
    },
    "times": {
      "daily_post": "00:00",
      "daily_scoreboard": "23:30",
      "weekly_roundup": "23:45",
      "rivalry": "14:00",
      "monthly_leaderboard": "00:10"
    },
    "minimum_days": {
      "this_week": 3,
      "this_month": 7,
      "all_time": 0,
      "date_range": 0
    },
    "last_run": {
      "daily_post": null,
      "daily_scoreboard": "2026-06-15",
      "weekly_roundup": "2026-05-31",
      "rivalry": "2026-06-20",
      "monthly_leaderboard": "2026-06-01"
    }
  },
  "1327237678466338932": {
    "enabled": true,
    "channel_id": 1488097289028243476,
    "admin_role_ids": [
      1328158928651157684
    ],
    "timezone": "Europe/London",
    "server_streak": {
      "current": 2,
      "best": 23,
      "last_score_date": "2026-06-12"
    },
    "alerts": {
      "daily_post_enabled": true,
      "daily_scoreboard_enabled": true,
      "weekly_roundup_enabled": true,
      "rivalry_enabled": true,
      "monthly_leaderboard_enabled": true,
      "zero_score_roasts_enabled": true,
      "pb_messages_enabled": true,
      "perfect_score_enabled": true
    },
    "emojis": {
      "recorded": "<:maptapp:1476982463430660136>",
      "too_high": "\u274c",
      "rescan_ingested": "\ud83d\udd01",
      "config_issue": "\u26a0\ufe0f"
    },
    "times": {
      "daily_post": "00:00",
      "daily_scoreboard": "23:30",
      "weekly_roundup": "23:45",
      "rivalry": "10:00",
      "monthly_leaderboard": "00:10"
    },
    "minimum_days": {
      "this_week": 3,
      "this_month": 7,
      "all_time": 0,
      "date_range": 0
    },
    "last_run": {
      "daily_post": "2026-06-16",
      "daily_scoreboard": "2026-06-15",
      "weekly_roundup": "2026-05-31",
      "rivalry": "2026-06-03",
      "monthly_leaderboard": "2026-06-01"
    }
  },
  "1493645966727974912": {
    "enabled": true,
    "channel_id": 1493652218249871490,
    "admin_role_ids": [
      1493645966740422744
    ],
    "timezone": "Europe/London",
    "server_streak": {
      "current": 0,
      "best": 0,
      "last_score_date": null
    },
    "alerts": {
      "daily_post_enabled": true,
      "daily_scoreboard_enabled": true,
      "weekly_roundup_enabled": true,
      "rivalry_enabled": true,
      "monthly_leaderboard_enabled": true,
      "zero_score_roasts_enabled": true,
      "pb_messages_enabled": true,
      "perfect_score_enabled": true
    },
    "emojis": {
      "recorded": "<:maptapp:1476982463430660136>",
      "too_high": "\u274c",
      "rescan_ingested": "\ud83d\udd01",
      "config_issue": "\u26a0\ufe0f"
    },
    "times": {
      "daily_post": "00:00",
      "daily_scoreboard": "23:30",
      "weekly_roundup": "23:45",
      "rivalry": "14:00",
      "monthly_leaderboard": "00:10"
    },
    "minimum_days": {
      "this_week": 3,
      "this_month": 7,
      "all_time": 0,
      "date_range": 0
    },
    "last_run": {
      "daily_post": "2026-06-16",
      "daily_scoreboard": "2026-06-15",
      "weekly_roundup": "2026-05-31",
      "rivalry": "2026-06-20",
      "monthly_leaderboard": "2026-06-01"
    }
  },
  "285278316993183746": {
    "enabled": true,
    "channel_id": 1465851165836185713,
    "admin_role_ids": [],
    "timezone": "Europe/London",
    "server_streak": {
      "current": 0,
      "best": 0,
      "last_score_date": null
    },
    "alerts": {
      "daily_post_enabled": false,
      "daily_scoreboard_enabled": false,
      "weekly_roundup_enabled": false,
      "rivalry_enabled": true,
      "monthly_leaderboard_enabled": false,
      "zero_score_roasts_enabled": true,
      "pb_messages_enabled": false,
      "perfect_score_enabled": false
    },
    "emojis": {
      "recorded": "\ud83c\udf0f",
      "too_high": "\u274c",
      "rescan_ingested": "\ud83d\udd01",
      "config_issue": "\u26a0\ufe0f"
    },
    "times": {
      "daily_post": "00:00",
      "daily_scoreboard": "23:30",
      "weekly_roundup": "23:45",
      "rivalry": "14:00",
      "monthly_leaderboard": "00:10"
    },
    "minimum_days": {
      "this_week": 3,
      "this_month": 7,
      "all_time": 0,
      "date_range": 0
    },
    "last_run": {
      "daily_post": null,
      "daily_scoreboard": null,
      "weekly_roundup": null,
      "rivalry": "2026-06-20",
      "monthly_leaderboard": null
    }
  },
  "1326160134006771722": {
    "enabled": true,
    "channel_id": 1495799045967315125,
    "admin_role_ids": [
      1326160426710597684
    ],
    "timezone": "Europe/London",
    "server_streak": {
      "current": 2,
      "best": 2,
      "last_score_date": "2026-04-21"
    },
    "alerts": {
      "daily_post_enabled": true,
      "daily_scoreboard_enabled": true,
      "weekly_roundup_enabled": true,
      "rivalry_enabled": true,
      "monthly_leaderboard_enabled": true,
      "zero_score_roasts_enabled": true,
      "pb_messages_enabled": true,
      "perfect_score_enabled": true
    },
    "emojis": {
      "recorded": "\ud83c\udf0f",
      "too_high": "\u274c",
      "rescan_ingested": "\ud83d\udd01",
      "config_issue": "\u26a0\ufe0f"
    },
    "times": {
      "daily_post": "00:00",
      "daily_scoreboard": "23:30",
      "weekly_roundup": "23:45",
      "rivalry": "14:00",
      "monthly_leaderboard": "00:10"
    },
    "minimum_days": {
      "this_week": 3,
      "this_month": 7,
      "all_time": 0,
      "date_range": 0
    },
    "last_run": {
      "daily_post": "2026-06-16",
      "daily_scoreboard": "2026-06-15",
      "weekly_roundup": "2026-05-31",
      "rivalry": "2026-06-20",
      "monthly_leaderboard": "2026-06-01"
    }
  },
  "1310666539942281267": {
    "enabled": true,
    "channel_id": 1499014116944379985,
    "admin_role_ids": [],
    "timezone": "Europe/London",
    "server_streak": {
      "current": 9,
      "best": 28,
      "last_score_date": "2026-06-21"
    },
    "alerts": {
      "daily_post_enabled": true,
      "daily_scoreboard_enabled": true,
      "weekly_roundup_enabled": true,
      "rivalry_enabled": true,
      "monthly_leaderboard_enabled": true,
      "zero_score_roasts_enabled": true,
      "pb_messages_enabled": true,
      "perfect_score_enabled": true
    },
    "emojis": {
      "recorded": "\ud83c\udf0f",
      "too_high": "\u274c",
      "rescan_ingested": "\ud83d\udd01",
      "config_issue": "\u26a0\ufe0f"
    },
    "times": {
      "daily_post": "00:00",
      "daily_scoreboard": "23:30",
      "weekly_roundup": "23:45",
      "rivalry": "14:00",
      "monthly_leaderboard": "00:10"
    },
    "minimum_days": {
      "this_week": 3,
      "this_month": 7,
      "all_time": 0,
      "date_range": 0
    },
    "last_run": {
      "daily_post": "2026-06-16",
      "daily_scoreboard": "2026-06-15",
      "weekly_roundup": "2026-05-31",
      "rivalry": "2026-06-20",
      "monthly_leaderboard": "2026-06-01"
    }
  },
  "208621163776049152": {
    "enabled": true,
    "channel_id": 1500209805938135131,
    "admin_role_ids": [
      296501465772589057,
      1432926777143070820
    ],
    "timezone": "Europe/London",
    "server_streak": {
      "current": 1,
      "best": 23,
      "last_score_date": "2026-06-20"
    },
    "alerts": {
      "daily_post_enabled": true,
      "daily_scoreboard_enabled": true,
      "weekly_roundup_enabled": true,
      "rivalry_enabled": true,
      "monthly_leaderboard_enabled": true,
      "zero_score_roasts_enabled": true,
      "pb_messages_enabled": true,
      "perfect_score_enabled": true
    },
    "emojis": {
      "recorded": "\ud83c\udf0f",
      "too_high": "\u274c",
      "rescan_ingested": "\ud83d\udd01",
      "config_issue": "\u26a0\ufe0f"
    },
    "times": {
      "daily_post": "00:00",
      "daily_scoreboard": "23:30",
      "weekly_roundup": "23:45",
      "rivalry": "14:00",
      "monthly_leaderboard": "00:10"
    },
    "minimum_days": {
      "this_week": 3,
      "this_month": 7,
      "all_time": 0,
      "date_range": 0
    },
    "last_run": {
      "daily_post": "2026-06-16",
      "daily_scoreboard": "2026-06-15",
      "weekly_roundup": "2026-05-31",
      "rivalry": "2026-06-20",
      "monthly_leaderboard": "2026-06-01"
    }
  },
  "1432531732552351768": {
    "enabled": true,
    "channel_id": null,
    "admin_role_ids": [],
    "timezone": "America/New_York",
    "server_streak": {
      "current": 0,
      "best": 0,
      "last_score_date": null
    },
    "alerts": {
      "daily_post_enabled": false,
      "daily_scoreboard_enabled": true,
      "weekly_roundup_enabled": false,
      "rivalry_enabled": true,
      "monthly_leaderboard_enabled": true,
      "zero_score_roasts_enabled": true,
      "pb_messages_enabled": true,
      "perfect_score_enabled": true
    },
    "emojis": {
      "recorded": "\ud83c\udf0f",
      "too_high": "\u274c",
      "rescan_ingested": "\ud83d\udd01",
      "config_issue": "\u26a0\ufe0f"
    },
    "times": {
      "daily_post": "00:00",
      "daily_scoreboard": "23:30",
      "weekly_roundup": "23:45",
      "rivalry": "14:00",
      "monthly_leaderboard": "00:10"
    },
    "minimum_days": {
      "this_week": 3,
      "this_month": 7,
      "all_time": 0,
      "date_range": 0
    },
    "last_run": {
      "daily_post": null,
      "daily_scoreboard": "2026-06-15",
      "weekly_roundup": null,
      "rivalry": "2026-06-20",
      "monthly_leaderboard": "2026-06-01"
    }
  },
  "370592567386963969": {
    "enabled": true,
    "channel_id": 1500686137784664104,
    "admin_role_ids": [],
    "timezone": "Europe/London",
    "server_streak": {
      "current": 48,
      "best": 48,
      "last_score_date": "2026-06-20"
    },
    "alerts": {
      "daily_post_enabled": true,
      "daily_scoreboard_enabled": true,
      "weekly_roundup_enabled": true,
      "rivalry_enabled": true,
      "monthly_leaderboard_enabled": true,
      "zero_score_roasts_enabled": true,
      "pb_messages_enabled": true,
      "perfect_score_enabled": true
    },
    "emojis": {
      "recorded": "\ud83c\udf0f",
      "too_high": "\u274c",
      "rescan_ingested": "\ud83d\udd01",
      "config_issue": "\u26a0\ufe0f"
    },
    "times": {
      "daily_post": "00:00",
      "daily_scoreboard": "23:30",
      "weekly_roundup": "23:45",
      "rivalry": "14:00",
      "monthly_leaderboard": "00:10"
    },
    "minimum_days": {
      "this_week": 3,
      "this_month": 7,
      "all_time": 0,
      "date_range": 0
    },
    "last_run": {
      "daily_post": "2026-06-16",
      "daily_scoreboard": "2026-06-15",
      "weekly_roundup": "2026-05-31",
      "rivalry": "2026-06-20",
      "monthly_leaderboard": "2026-06-01"
    }
  },
  "502562070684893195": {
    "enabled": true,
    "channel_id": 1500932519888031857,
    "admin_role_ids": [
      1088570189626474508
    ],
    "timezone": "America/New_York",
    "server_streak": {
      "current": 49,
      "best": 49,
      "last_score_date": "2026-06-21"
    },
    "alerts": {
      "daily_post_enabled": true,
      "daily_scoreboard_enabled": true,
      "weekly_roundup_enabled": true,
      "rivalry_enabled": true,
      "monthly_leaderboard_enabled": true,
      "zero_score_roasts_enabled": true,
      "pb_messages_enabled": true,
      "perfect_score_enabled": true
    },
    "emojis": {
      "recorded": "\ud83c\udf0f",
      "too_high": "\u274c",
      "rescan_ingested": "\ud83d\udd01",
      "config_issue": "\u26a0\ufe0f"
    },
    "times": {
      "daily_post": "12:00",
      "daily_scoreboard": "22:30",
      "weekly_roundup": "22:30",
      "rivalry": "14:00",
      "monthly_leaderboard": "10:00"
    },
    "minimum_days": {
      "this_week": 3,
      "this_month": 7,
      "all_time": 0,
      "date_range": 0
    },
    "last_run": {
      "daily_post": "2026-06-18",
      "daily_scoreboard": "2026-06-15",
      "weekly_roundup": "2026-05-31",
      "rivalry": "2026-06-20",
      "monthly_leaderboard": null
    }
  },
  "690246239974981759": {
    "enabled": true,
    "channel_id": 1501031815463440515,
    "admin_role_ids": [
      690340514750660662
    ],
    "timezone": "Europe/London",
    "server_streak": {
      "current": 45,
      "best": 45,
      "last_score_date": "2026-06-20"
    },
    "alerts": {
      "daily_post_enabled": true,
      "daily_scoreboard_enabled": true,
      "weekly_roundup_enabled": true,
      "rivalry_enabled": true,
      "monthly_leaderboard_enabled": true,
      "zero_score_roasts_enabled": true,
      "pb_messages_enabled": true,
      "perfect_score_enabled": true
    },
    "emojis": {
      "recorded": "\ud83c\udf0f",
      "too_high": "\u274c",
      "rescan_ingested": "\ud83d\udd01",
      "config_issue": "\u26a0\ufe0f"
    },
    "times": {
      "daily_post": "07:00",
      "daily_scoreboard": "20:00",
      "weekly_roundup": "20:00",
      "rivalry": "14:00",
      "monthly_leaderboard": "07:00"
    },
    "minimum_days": {
      "this_week": 3,
      "this_month": 7,
      "all_time": 0,
      "date_range": 0
    },
    "last_run": {
      "daily_post": "2026-06-16",
      "daily_scoreboard": "2026-06-20",
      "weekly_roundup": "2026-05-31",
      "rivalry": "2026-06-20",
      "monthly_leaderboard": "2026-06-01"
    }
  },
  "264137661340581888": {
    "enabled": true,
    "channel_id": 264137661340581888,
    "admin_role_ids": [
      264143330856796160
    ],
    "timezone": "Europe/London",
    "server_streak": {
      "current": 42,
      "best": 42,
      "last_score_date": "2026-06-20"
    },
    "alerts": {
      "daily_post_enabled": true,
      "daily_scoreboard_enabled": false,
      "weekly_roundup_enabled": true,
      "rivalry_enabled": false,
      "monthly_leaderboard_enabled": true,
      "zero_score_roasts_enabled": false,
      "pb_messages_enabled": false,
      "perfect_score_enabled": true
    },
    "emojis": {
      "recorded": "\ud83c\udf0f",
      "too_high": "\u274c",
      "rescan_ingested": "\ud83d\udd01",
      "config_issue": "\u26a0\ufe0f"
    },
    "times": {
      "daily_post": "07:00",
      "daily_scoreboard": "13:30",
      "weekly_roundup": "18:00",
      "rivalry": "14:00",
      "monthly_leaderboard": "00:10"
    },
    "minimum_days": {
      "this_week": 3,
      "this_month": 7,
      "all_time": 0,
      "date_range": 0
    },
    "last_run": {
      "daily_post": "2026-06-16",
      "daily_scoreboard": "2026-05-18",
      "weekly_roundup": "2026-05-31",
      "rivalry": "2026-05-18",
      "monthly_leaderboard": "2026-06-01"
    }
  },
  "357281973007548428": {
    "enabled": true,
    "channel_id": 372161729532133376,
    "admin_role_ids": [
      357284086819323914
    ],
    "timezone": "EST",
    "server_streak": {
      "current": 43,
      "best": 43,
      "last_score_date": "2026-06-20"
    },
    "alerts": {
      "daily_post_enabled": true,
      "daily_scoreboard_enabled": true,
      "weekly_roundup_enabled": true,
      "rivalry_enabled": true,
      "monthly_leaderboard_enabled": true,
      "zero_score_roasts_enabled": true,
      "pb_messages_enabled": true,
      "perfect_score_enabled": true
    },
    "emojis": {
      "recorded": "\ud83c\udf0f",
      "too_high": "\u274c",
      "rescan_ingested": "\ud83d\udd01",
      "config_issue": "\u26a0\ufe0f"
    },
    "times": {
      "daily_post": "07:00",
      "daily_scoreboard": "18:00",
      "weekly_roundup": "18:00",
      "rivalry": "14:00",
      "monthly_leaderboard": "07:00"
    },
    "minimum_days": {
      "this_week": 3,
      "this_month": 7,
      "all_time": 0,
      "date_range": 0
    },
    "last_run": {
      "daily_post": "2026-06-20",
      "daily_scoreboard": "2026-06-15",
      "weekly_roundup": "2026-05-31",
      "rivalry": "2026-06-20",
      "monthly_leaderboard": "2026-06-01"
    }
  },
  "1503675560126054440": {
    "enabled": true,
    "channel_id": 1503675561283686554,
    "admin_role_ids": [],
    "timezone": "Europe/London",
    "server_streak": {
      "current": 0,
      "best": 0,
      "last_score_date": null
    },
    "alerts": {
      "daily_post_enabled": true,
      "daily_scoreboard_enabled": true,
      "weekly_roundup_enabled": true,
      "rivalry_enabled": true,
      "monthly_leaderboard_enabled": true,
      "zero_score_roasts_enabled": true,
      "pb_messages_enabled": true,
      "perfect_score_enabled": true
    },
    "emojis": {
      "recorded": "\ud83c\udf0f",
      "too_high": "\u274c",
      "rescan_ingested": "\ud83d\udd01",
      "config_issue": "\u26a0\ufe0f"
    },
    "times": {
      "daily_post": "00:00",
      "daily_scoreboard": "23:30",
      "weekly_roundup": "23:45",
      "rivalry": "14:00",
      "monthly_leaderboard": "00:10"
    },
    "minimum_days": {
      "this_week": 3,
      "this_month": 7,
      "all_time": 0,
      "date_range": 0
    },
    "last_run": {
      "daily_post": "2026-06-16",
      "daily_scoreboard": "2026-06-15",
      "weekly_roundup": "2026-05-31",
      "rivalry": "2026-06-20",
      "monthly_leaderboard": "2026-06-01"
    }
  },
  "1465035461956473108": {
    "enabled": true,
    "channel_id": 1496979389705883678,
    "admin_role_ids": [
      1496147911774568521,
      1496147789560807434
    ],
    "timezone": "Europe/London",
    "server_streak": {
      "current": 1,
      "best": 12,
      "last_score_date": "2026-06-10"
    },
    "alerts": {
      "daily_post_enabled": true,
      "daily_scoreboard_enabled": true,
      "weekly_roundup_enabled": true,
      "rivalry_enabled": true,
      "monthly_leaderboard_enabled": true,
      "zero_score_roasts_enabled": true,
      "pb_messages_enabled": true,
      "perfect_score_enabled": true
    },
    "emojis": {
      "recorded": "\ud83c\udf0f",
      "too_high": "\u274c",
      "rescan_ingested": "\ud83d\udd01",
      "config_issue": "\u26a0\ufe0f"
    },
    "times": {
      "daily_post": "10:30",
      "daily_scoreboard": "21:00",
      "weekly_roundup": "19:30",
      "rivalry": "14:00",
      "monthly_leaderboard": "00:10"
    },
    "minimum_days": {
      "this_week": 3,
      "this_month": 7,
      "all_time": 0,
      "date_range": 0
    },
    "last_run": {
      "daily_post": "2026-06-20",
      "daily_scoreboard": "2026-06-20",
      "weekly_roundup": "2026-05-31",
      "rivalry": "2026-06-20",
      "monthly_leaderboard": "2026-06-01"
    }
  },
  "691043374454538301": {
    "enabled": true,
    "channel_id": 1504095538763792394,
    "admin_role_ids": [
      691043761643585669
    ],
    "timezone": "America/New_York",
    "server_streak": {
      "current": 39,
      "best": 39,
      "last_score_date": "2026-06-20"
    },
    "alerts": {
      "daily_post_enabled": true,
      "daily_scoreboard_enabled": true,
      "weekly_roundup_enabled": true,
      "rivalry_enabled": true,
      "monthly_leaderboard_enabled": true,
      "zero_score_roasts_enabled": true,
      "pb_messages_enabled": true,
      "perfect_score_enabled": true
    },
    "emojis": {
      "recorded": "\ud83c\udf0f",
      "too_high": "\u274c",
      "rescan_ingested": "\ud83d\udd01",
      "config_issue": "\u26a0\ufe0f"
    },
    "times": {
      "daily_post": "00:00",
      "daily_scoreboard": "23:30",
      "weekly_roundup": "23:45",
      "rivalry": "14:00",
      "monthly_leaderboard": "00:10"
    },
    "minimum_days": {
      "this_week": 3,
      "this_month": 7,
      "all_time": 0,
      "date_range": 0
    },
    "last_run": {
      "daily_post": "2026-06-16",
      "daily_scoreboard": "2026-06-15",
      "weekly_roundup": "2026-05-31",
      "rivalry": "2026-06-20",
      "monthly_leaderboard": "2026-06-01"
    }
  },
  "949035284559982612": {
    "enabled": true,
    "channel_id": 1504538290005737555,
    "admin_role_ids": [
      949035284559982617
    ],
    "timezone": "Europe/London",
    "server_streak": {
      "current": 14,
      "best": 14,
      "last_score_date": "2026-05-27"
    },
    "alerts": {
      "daily_post_enabled": true,
      "daily_scoreboard_enabled": true,
      "weekly_roundup_enabled": true,
      "rivalry_enabled": true,
      "monthly_leaderboard_enabled": true,
      "zero_score_roasts_enabled": true,
      "pb_messages_enabled": true,
      "perfect_score_enabled": true
    },
    "emojis": {
      "recorded": "\ud83c\udf0f",
      "too_high": "\u274c",
      "rescan_ingested": "\ud83d\udd01",
      "config_issue": "\u26a0\ufe0f"
    },
    "times": {
      "daily_post": "00:00",
      "daily_scoreboard": "23:30",
      "weekly_roundup": "23:45",
      "rivalry": "14:00",
      "monthly_leaderboard": "00:10"
    },
    "minimum_days": {
      "this_week": 3,
      "this_month": 7,
      "all_time": 0,
      "date_range": 0
    },
    "last_run": {
      "daily_post": "2026-06-16",
      "daily_scoreboard": "2026-06-15",
      "weekly_roundup": "2026-05-31",
      "rivalry": "2026-06-20",
      "monthly_leaderboard": "2026-06-01"
    }
  },
  "748815933195157555": {
    "enabled": true,
    "channel_id": 832676939440717836,
    "admin_role_ids": [],
    "timezone": "Europe/London",
    "server_streak": {
      "current": 1,
      "best": 1,
      "last_score_date": "2026-06-01"
    },
    "alerts": {
      "daily_post_enabled": true,
      "daily_scoreboard_enabled": true,
      "weekly_roundup_enabled": true,
      "rivalry_enabled": true,
      "monthly_leaderboard_enabled": false,
      "zero_score_roasts_enabled": true,
      "pb_messages_enabled": true,
      "perfect_score_enabled": true
    },
    "emojis": {
      "recorded": "\ud83c\udf0f",
      "too_high": "\u274c",
      "rescan_ingested": "\ud83d\udd01",
      "config_issue": "\u26a0\ufe0f"
    },
    "times": {
      "daily_post": "00:00",
      "daily_scoreboard": "23:30",
      "weekly_roundup": "23:45",
      "rivalry": "14:00",
      "monthly_leaderboard": "00:10"
    },
    "minimum_days": {
      "this_week": 3,
      "this_month": 7,
      "all_time": 0,
      "date_range": 0
    },
    "last_run": {
      "daily_post": "2026-06-16",
      "daily_scoreboard": "2026-06-15",
      "weekly_roundup": null,
      "rivalry": "2026-06-20",
      "monthly_leaderboard": null
    }
  },
  "663566501684445184": {
    "enabled": true,
    "channel_id": 663566501684445189,
    "admin_role_ids": [],
    "timezone": "Europe/London",
    "server_streak": {
      "current": 0,
      "best": 0,
      "last_score_date": null
    },
    "alerts": {
      "daily_post_enabled": true,
      "daily_scoreboard_enabled": true,
      "weekly_roundup_enabled": true,
      "rivalry_enabled": true,
      "monthly_leaderboard_enabled": true,
      "zero_score_roasts_enabled": true,
      "pb_messages_enabled": true,
      "perfect_score_enabled": true
    },
    "emojis": {
      "recorded": "\ud83c\udf0f",
      "too_high": "\u274c",
      "rescan_ingested": "\ud83d\udd01",
      "config_issue": "\u26a0\ufe0f"
    },
    "times": {
      "daily_post": "10:00",
      "daily_scoreboard": "22:00",
      "weekly_roundup": "22:00",
      "rivalry": "14:00",
      "monthly_leaderboard": "10:00"
    },
    "minimum_days": {
      "this_week": 3,
      "this_month": 7,
      "all_time": 0,
      "date_range": 0
    },
    "last_run": {
      "daily_post": null,
      "daily_scoreboard": null,
      "weekly_roundup": null,
      "rivalry": "2026-06-20",
      "monthly_leaderboard": null
    }
  },
  "1160169538910957708": {
    "enabled": true,
    "channel_id": 1512379829947994253,
    "admin_role_ids": [
      1160170329994432554
    ],
    "timezone": "Europe/London",
    "server_streak": {
      "current": 16,
      "best": 16,
      "last_score_date": "2026-06-20"
    },
    "alerts": {
      "daily_post_enabled": true,
      "daily_scoreboard_enabled": true,
      "weekly_roundup_enabled": true,
      "rivalry_enabled": true,
      "monthly_leaderboard_enabled": true,
      "zero_score_roasts_enabled": true,
      "pb_messages_enabled": true,
      "perfect_score_enabled": true
    },
    "emojis": {
      "recorded": "\ud83c\udf0f",
      "too_high": "\u274c",
      "rescan_ingested": "\ud83d\udd01",
      "config_issue": "\u26a0\ufe0f"
    },
    "times": {
      "daily_post": "00:00",
      "daily_scoreboard": "23:30",
      "weekly_roundup": "23:45",
      "rivalry": "14:00",
      "monthly_leaderboard": "00:10"
    },
    "minimum_days": {
      "this_week": 3,
      "this_month": 7,
      "all_time": 0,
      "date_range": 0
    },
    "last_run": {
      "daily_post": "2026-06-16",
      "daily_scoreboard": null,
      "weekly_roundup": null,
      "rivalry": "2026-06-20",
      "monthly_leaderboard": null
    }
  },
  "1376154352707829770": {
    "enabled": true,
    "channel_id": 1376154352707829772,
    "admin_role_ids": [],
    "timezone": "Europe/London",
    "server_streak": {
      "current": 16,
      "best": 16,
      "last_score_date": "2026-06-21"
    },
    "alerts": {
      "daily_post_enabled": true,
      "daily_scoreboard_enabled": true,
      "weekly_roundup_enabled": true,
      "rivalry_enabled": true,
      "monthly_leaderboard_enabled": true,
      "zero_score_roasts_enabled": false,
      "pb_messages_enabled": true,
      "perfect_score_enabled": true
    },
    "emojis": {
      "recorded": "\ud83c\udf0f",
      "too_high": "\u274c",
      "rescan_ingested": "\ud83d\udd01",
      "config_issue": "\u26a0\ufe0f"
    },
    "times": {
      "daily_post": "06:00",
      "daily_scoreboard": "23:30",
      "weekly_roundup": "23:45",
      "rivalry": "14:00",
      "monthly_leaderboard": "00:10"
    },
    "minimum_days": {
      "this_week": 3,
      "this_month": 7,
      "all_time": 0,
      "date_range": 0
    },
    "last_run": {
      "daily_post": "2026-06-16",
      "daily_scoreboard": null,
      "weekly_roundup": null,
      "rivalry": "2026-06-20",
      "monthly_leaderboard": null
    }
  },
  "1129126011028639894": {
    "enabled": true,
    "channel_id": 1142554493691637802,
    "admin_role_ids": [
      1158574348777562183
    ],
    "timezone": "Europe/London",
    "server_streak": {
      "current": 1,
      "best": 4,
      "last_score_date": "2026-06-11"
    },
    "alerts": {
      "daily_post_enabled": true,
      "daily_scoreboard_enabled": true,
      "weekly_roundup_enabled": true,
      "rivalry_enabled": true,
      "monthly_leaderboard_enabled": true,
      "zero_score_roasts_enabled": true,
      "pb_messages_enabled": true,
      "perfect_score_enabled": true
    },
    "emojis": {
      "recorded": "\ud83c\udf0f",
      "too_high": "\u274c",
      "rescan_ingested": "\ud83d\udd01",
      "config_issue": "\u26a0\ufe0f"
    },
    "times": {
      "daily_post": "00:00",
      "daily_scoreboard": "23:30",
      "weekly_roundup": "23:45",
      "rivalry": "14:00",
      "monthly_leaderboard": "00:10"
    },
    "minimum_days": {
      "this_week": 3,
      "this_month": 7,
      "all_time": 0,
      "date_range": 0
    },
    "last_run": {
      "daily_post": "2026-06-16",
      "daily_scoreboard": null,
      "weekly_roundup": null,
      "rivalry": "2026-06-20",
      "monthly_leaderboard": null
    }
  },
  "1513583359589220573": {
    "enabled": true,
    "channel_id": 1513584127247646721,
    "admin_role_ids": [],
    "timezone": "Europe/London",
    "server_streak": {
      "current": 1,
      "best": 6,
      "last_score_date": "2026-06-16"
    },
    "alerts": {
      "daily_post_enabled": true,
      "daily_scoreboard_enabled": true,
      "weekly_roundup_enabled": true,
      "rivalry_enabled": true,
      "monthly_leaderboard_enabled": true,
      "zero_score_roasts_enabled": true,
      "pb_messages_enabled": true,
      "perfect_score_enabled": true
    },
    "emojis": {
      "recorded": "\ud83c\udf0f",
      "too_high": "\u274c",
      "rescan_ingested": "\ud83d\udd01",
      "config_issue": "\u26a0\ufe0f"
    },
    "times": {
      "daily_post": "00:00",
      "daily_scoreboard": "23:30",
      "weekly_roundup": "23:45",
      "rivalry": "14:00",
      "monthly_leaderboard": "00:10"
    },
    "minimum_days": {
      "this_week": 3,
      "this_month": 7,
      "all_time": 0,
      "date_range": 0
    },
    "last_run": {
      "daily_post": "2026-06-16",
      "daily_scoreboard": null,
      "weekly_roundup": null,
      "rivalry": "2026-06-20",
      "monthly_leaderboard": null
    }
  },
  "1013863951081152632": {
    "enabled": true,
    "channel_id": 1512852372785991680,
    "admin_role_ids": [],
    "timezone": "America/Chicago",
    "server_streak": {
      "current": 12,
      "best": 12,
      "last_score_date": "2026-06-20"
    },
    "alerts": {
      "daily_post_enabled": true,
      "daily_scoreboard_enabled": true,
      "weekly_roundup_enabled": true,
      "rivalry_enabled": true,
      "monthly_leaderboard_enabled": true,
      "zero_score_roasts_enabled": true,
      "pb_messages_enabled": true,
      "perfect_score_enabled": true
    },
    "emojis": {
      "recorded": "\ud83c\udf0f",
      "too_high": "\u274c",
      "rescan_ingested": "\ud83d\udd01",
      "config_issue": "\u26a0\ufe0f"
    },
    "times": {
      "daily_post": "00:00",
      "daily_scoreboard": "23:30",
      "weekly_roundup": "23:45",
      "rivalry": "14:00",
      "monthly_leaderboard": "00:10"
    },
    "minimum_days": {
      "this_week": 3,
      "this_month": 7,
      "all_time": 0,
      "date_range": 0
    },
    "last_run": {
      "daily_post": "2026-06-16",
      "daily_scoreboard": "2026-06-15",
      "weekly_roundup": "2026-06-14",
      "rivalry": "2026-06-20",
      "monthly_leaderboard": null
    }
  },
  "1271246140804698172": {
    "enabled": true,
    "channel_id": 1514210567945060402,
    "admin_role_ids": [
      1514210431340904452
    ],
    "timezone": "Europe/London",
    "server_streak": {
      "current": 9,
      "best": 9,
      "last_score_date": "2026-06-21"
    },
    "alerts": {
      "daily_post_enabled": true,
      "daily_scoreboard_enabled": true,
      "weekly_roundup_enabled": false,
      "rivalry_enabled": false,
      "monthly_leaderboard_enabled": true,
      "zero_score_roasts_enabled": false,
      "pb_messages_enabled": true,
      "perfect_score_enabled": false
    },
    "emojis": {
      "recorded": "\ud83c\udf0f",
      "too_high": "\u274c",
      "rescan_ingested": "\ud83d\udd01",
      "config_issue": "\u26a0\ufe0f"
    },
    "times": {
      "daily_post": "00:00",
      "daily_scoreboard": "23:30",
      "weekly_roundup": "23:45",
      "rivalry": "14:00",
      "monthly_leaderboard": "00:10"
    },
    "minimum_days": {
      "this_week": 3,
      "this_month": 7,
      "all_time": 0,
      "date_range": 0
    },
    "last_run": {
      "daily_post": "2026-06-16",
      "daily_scoreboard": null,
      "weekly_roundup": null,
      "rivalry": "2026-06-12",
      "monthly_leaderboard": null
    }
  },
  "1370420547757801502": {
    "enabled": true,
    "channel_id": 1370420548353528001,
    "admin_role_ids": [],
    "timezone": "America/New_York",
    "server_streak": {
      "current": 6,
      "best": 6,
      "last_score_date": "2026-06-20"
    },
    "alerts": {
      "daily_post_enabled": true,
      "daily_scoreboard_enabled": true,
      "weekly_roundup_enabled": true,
      "rivalry_enabled": true,
      "monthly_leaderboard_enabled": true,
      "zero_score_roasts_enabled": true,
      "pb_messages_enabled": true,
      "perfect_score_enabled": true
    },
    "emojis": {
      "recorded": "\ud83c\udf0f",
      "too_high": "\u274c",
      "rescan_ingested": "\ud83d\udd01",
      "config_issue": "\u26a0\ufe0f"
    },
    "times": {
      "daily_post": "10:00",
      "daily_scoreboard": "20:00",
      "weekly_roundup": "20:00",
      "rivalry": "20:00",
      "monthly_leaderboard": "10:00"
    },
    "minimum_days": {
      "this_week": 3,
      "this_month": 7,
      "all_time": 0,
      "date_range": 0
    },
    "last_run": {
      "daily_post": "2026-06-20",
      "daily_scoreboard": "2026-06-15",
      "weekly_roundup": null,
      "rivalry": null,
      "monthly_leaderboard": null
    }
  },
  "537671186856017923": {
    "enabled": true,
    "channel_id": 1516102713232982078,
    "admin_role_ids": [
      895770933258756147,
      881950452751691776,
      683760376197808133,
      621819514723631117,
      568746358056419344,
      538430153462644768,
      537675583140921364,
      1516102267520946404,
      1361776252163461383
    ],
    "timezone": "Europe/Amsterdam",
    "server_streak": {
      "current": 6,
      "best": 6,
      "last_score_date": "2026-06-20"
    },
    "alerts": {
      "daily_post_enabled": false,
      "daily_scoreboard_enabled": false,
      "weekly_roundup_enabled": false,
      "rivalry_enabled": true,
      "monthly_leaderboard_enabled": false,
      "zero_score_roasts_enabled": true,
      "pb_messages_enabled": true,
      "perfect_score_enabled": true
    },
    "emojis": {
      "recorded": "\ud83c\udf0f",
      "too_high": "\u274c",
      "rescan_ingested": "\ud83d\udd01",
      "config_issue": "\u26a0\ufe0f"
    },
    "times": {
      "daily_post": "00:00",
      "daily_scoreboard": "23:30",
      "weekly_roundup": "23:45",
      "rivalry": "14:00",
      "monthly_leaderboard": "00:10"
    },
    "minimum_days": {
      "this_week": 3,
      "this_month": 7,
      "all_time": 0,
      "date_range": 0
    },
    "last_run": {
      "daily_post": "2026-06-16",
      "daily_scoreboard": "2026-06-15",
      "weekly_roundup": null,
      "rivalry": "2026-06-20",
      "monthly_leaderboard": null
    }
  },
  "700111731061555321": {
    "enabled": true,
    "channel_id": 933124617504182314,
    "admin_role_ids": [],
    "timezone": "Europe/London",
    "server_streak": {
      "current": 1,
      "best": 1,
      "last_score_date": "2026-06-16"
    },
    "alerts": {
      "daily_post_enabled": false,
      "daily_scoreboard_enabled": true,
      "weekly_roundup_enabled": true,
      "rivalry_enabled": true,
      "monthly_leaderboard_enabled": true,
      "zero_score_roasts_enabled": true,
      "pb_messages_enabled": false,
      "perfect_score_enabled": true
    },
    "emojis": {
      "recorded": "\ud83c\udf0f",
      "too_high": "\u274c",
      "rescan_ingested": "\ud83d\udd01",
      "config_issue": "\u26a0\ufe0f"
    },
    "times": {
      "daily_post": "00:00",
      "daily_scoreboard": "23:30",
      "weekly_roundup": "23:45",
      "rivalry": "14:00",
      "monthly_leaderboard": "00:10"
    },
    "minimum_days": {
      "this_week": 3,
      "this_month": 7,
      "all_time": 0,
      "date_range": 0
    },
    "last_run": {
      "daily_post": null,
      "daily_scoreboard": null,
      "weekly_roundup": null,
      "rivalry": "2026-06-20",
      "monthly_leaderboard": null
    }
  },
  "152269824872022017": {
    "enabled": true,
    "channel_id": 974075403587186708,
    "admin_role_ids": [
      506626702911471616
    ],
    "timezone": "US/Central",
    "server_streak": {
      "current": 5,
      "best": 5,
      "last_score_date": "2026-06-21"
    },
    "alerts": {
      "daily_post_enabled": true,
      "daily_scoreboard_enabled": false,
      "weekly_roundup_enabled": true,
      "rivalry_enabled": true,
      "monthly_leaderboard_enabled": true,
      "zero_score_roasts_enabled": true,
      "pb_messages_enabled": false,
      "perfect_score_enabled": false
    },
    "emojis": {
      "recorded": "\ud83c\udf0f",
      "too_high": "\u274c",
      "rescan_ingested": "\ud83d\udd01",
      "config_issue": "\u26a0\ufe0f"
    },
    "times": {
      "daily_post": "08:00",
      "daily_scoreboard": "23:30",
      "weekly_roundup": "23:45",
      "rivalry": "14:00",
      "monthly_leaderboard": "00:10"
    },
    "minimum_days": {
      "this_week": 3,
      "this_month": 7,
      "all_time": 0,
      "date_range": 0
    },
    "last_run": {
      "daily_post": "2026-06-20",
      "daily_scoreboard": null,
      "weekly_roundup": null,
      "rivalry": "2026-06-20",
      "monthly_leaderboard": null
    }
  },
  "777586930996477963": {
    "enabled": true,
    "channel_id": 1516839199712612413,
    "admin_role_ids": [
      1516838555438026772
    ],
    "timezone": "America/Chicago",
    "server_streak": {
      "current": 1,
      "best": 1,
      "last_score_date": "2026-06-18"
    },
    "alerts": {
      "daily_post_enabled": true,
      "daily_scoreboard_enabled": true,
      "weekly_roundup_enabled": true,
      "rivalry_enabled": true,
      "monthly_leaderboard_enabled": true,
      "zero_score_roasts_enabled": true,
      "pb_messages_enabled": true,
      "perfect_score_enabled": true
    },
    "emojis": {
      "recorded": "\ud83c\udf0f",
      "too_high": "\u274c",
      "rescan_ingested": "\ud83d\udd01",
      "config_issue": "\u26a0\ufe0f"
    },
    "times": {
      "daily_post": "00:00",
      "daily_scoreboard": "23:30",
      "weekly_roundup": "23:45",
      "rivalry": "14:00",
      "monthly_leaderboard": "00:10"
    },
    "minimum_days": {
      "this_week": 3,
      "this_month": 7,
      "all_time": 0,
      "date_range": 0
    },
    "last_run": {
      "daily_post": null,
      "daily_scoreboard": null,
      "weekly_roundup": null,
      "rivalry": "2026-06-20",
      "monthly_leaderboard": null
    }
  },
  "611426416646553614": {
    "enabled": true,
    "channel_id": 1516777218569666684,
    "admin_role_ids": [
      1516919214987018401
    ],
    "timezone": "Europe/London",
    "server_streak": {
      "current": 4,
      "best": 4,
      "last_score_date": "2026-06-21"
    },
    "alerts": {
      "daily_post_enabled": true,
      "daily_scoreboard_enabled": true,
      "weekly_roundup_enabled": true,
      "rivalry_enabled": true,
      "monthly_leaderboard_enabled": true,
      "zero_score_roasts_enabled": true,
      "pb_messages_enabled": true,
      "perfect_score_enabled": true
    },
    "emojis": {
      "recorded": "\ud83c\udf0f",
      "too_high": "\u274c",
      "rescan_ingested": "\ud83d\udd01",
      "config_issue": "\u26a0\ufe0f"
    },
    "times": {
      "daily_post": "00:00",
      "daily_scoreboard": "23:30",
      "weekly_roundup": "23:45",
      "rivalry": "14:00",
      "monthly_leaderboard": "00:10"
    },
    "minimum_days": {
      "this_week": 3,
      "this_month": 7,
      "all_time": 0,
      "date_range": 0
    },
    "last_run": {
      "daily_post": null,
      "daily_scoreboard": null,
      "weekly_roundup": null,
      "rivalry": "2026-06-20",
      "monthly_leaderboard": null
    }
  }
}